Metadata-Version: 2.1
Name: jcl-mmcv
Version: 1.3.16
Summary: test mmcv
Home-page: https://github.com/open-mmlab/mmcv
Author: JCL
Author-email: jamesliang819@gmail.com
License: UNKNOWN
Keywords: computer vision
Platform: UNKNOWN
Classifier: Development Status :: 4 - Beta
Classifier: License :: OSI Approved :: Apache Software License
Classifier: Operating System :: OS Independent
Classifier: Programming Language :: Python :: 3
Classifier: Programming Language :: Python :: 3.6
Classifier: Programming Language :: Python :: 3.7
Classifier: Programming Language :: Python :: 3.8
Classifier: Programming Language :: Python :: 3.9
Classifier: Topic :: Utilities
License-File: LICENSE
License-File: LICENSES.md
Requires-Dist: addict
Requires-Dist: numpy
Requires-Dist: packaging
Requires-Dist: Pillow
Requires-Dist: pyyaml
Requires-Dist: yapf
Requires-Dist: regex ; sys_platform == "win32"
